gradient_boosting_model/VERSION
gradient_boosting_model/__init__.py
gradient_boosting_model/config.yml
gradient_boosting_model/pipeline.py
gradient_boosting_model/predict.py
gradient_boosting_model/train_pipeline.py
gradient_boosting_model/config/__init__.py
gradient_boosting_model/config/core.py
gradient_boosting_model/datasets/__init__.py
gradient_boosting_model/datasets/houseprice.csv
gradient_boosting_model/datasets/test.csv
gradient_boosting_model/processing/__init__.py
gradient_boosting_model/processing/data_management.py
gradient_boosting_model/processing/errors.py
gradient_boosting_model/processing/preprocessors.py
gradient_boosting_model/processing/validation.py
gradient_boosting_model/trained_models/__init__.py
gradient_boosting_model/trained_models/gb_regression_output_v0.3.0.pkl
tid_gradient_boosting_model-0.3.0.dist-info/METADATA
tid_gradient_boosting_model-0.3.0.dist-info/WHEEL
tid_gradient_boosting_model-0.3.0.dist-info/top_level.txt
tid_gradient_boosting_model-0.3.0.dist-info/RECORD
